pydftools/__init__.py
pydftools/cli.py
pydftools/dffit.py
pydftools/mockdata.py
pydftools/model.py
pydftools/plotting.py
pydftools/selection.py
pydftools/utils.py
pydftools-0.1.0.dist-info/DESCRIPTION.rst
pydftools-0.1.0.dist-info/METADATA
pydftools-0.1.0.dist-info/RECORD
pydftools-0.1.0.dist-info/WHEEL
pydftools-0.1.0.dist-info/entry_points.txt
pydftools-0.1.0.dist-info/metadata.json
pydftools-0.1.0.dist-info/top_level.txt
