Metadata-Version: 2.0
Name: pydftools
Version: 0.1.0
Summary: A pure-python port of the dftools R package.
Home-page: https://github.com/steven-murray/pydftools
Author: Steven Murray
Author-email: steven.murray@curtin.edu.au
License: MIT license
Keywords: pydftools
Platform: UNKNOWN
Classifier: Development Status :: 2 - Pre-Alpha
Classifier: Intended Audience :: Developers
Classifier: License :: OSI Approved :: MIT License
Classifier: Natural Language :: English
Classifier: Programming Language :: Python :: 2
Classifier: Programming Language :: Python :: 2.6
Classifier: Programming Language :: Python :: 2.7
Classifier: Programming Language :: Python :: 3
Classifier: Programming Language :: Python :: 3.3
Classifier: Programming Language :: Python :: 3.4
Classifier: Programming Language :: Python :: 3.5
Requires-Dist: Click (>=6.0)
Requires-Dist: attrs (>=17.0)
Requires-Dist: cached-property
Requires-Dist: chainconsumer
Requires-Dist: numpy (>=1.6.2)
Requires-Dist: scipy
